groupBug-0.3.data/scripts/groupBug.py
groupBug-0.3.dist-info/METADATA
groupBug-0.3.dist-info/RECORD
groupBug-0.3.dist-info/WHEEL
groupBug-0.3.dist-info/top_level.txt
tests/__init__.py
tests/test_getDomain.py
